empower/__init__.py
empower/_core.py
empower/_trait.py
empower-0.2.1.dist-info/LICENSE
empower-0.2.1.dist-info/WHEEL
empower-0.2.1.dist-info/METADATA
empower-0.2.1.dist-info/RECORD
