Metadata-Version: 2.1
Name: empower
Version: 0.2.1
Summary: Goodbye Inheritance
License: Apache-2.0
Author: ZhengYu, Xu
Author-email: zen-xu@outlook.com
Requires-Python: >=3.7,<4.0
Classifier: License :: OSI Approved :: Apache Software License
Classifier: Programming Language :: Python :: 3
Classifier: Programming Language :: Python :: 3.10
Classifier: Programming Language :: Python :: 3.7
Classifier: Programming Language :: Python :: 3.8
Classifier: Programming Language :: Python :: 3.9
Requires-Dist: pytest (>=7.1.3,<8.0.0)
Requires-Dist: wrapt (>=1.11,<2.0)
